hf_chat/__init__.py
hf_chat/main.py
hf_chat/exceptions/__init__.py
hf_chat/exceptions/inference_failed_exception.py
hf_chat/exceptions/interaction_fail_exception.py
hf_chat/exceptions/login_exception.py
hf_chat-0.1.0.dist-info/METADATA
hf_chat-0.1.0.dist-info/WHEEL
hf_chat-0.1.0.dist-info/licenses/LICENSE
hf_chat-0.1.0.dist-info/RECORD
