Metadata-Version: 2.1
Name: hf-chat
Version: 0.1.0
Summary: Unofficial Huggingface chat async wrapper for reverse engineered api
Project-URL: Homepage, https://github.com/LyubimovVladislav/hf-chat
Project-URL: Bug Tracker, https://github.com/LyubimovVladislav/hf-chat/issues
Author-email: Vladislav Lyubimov <grifon7676@gmail.com>
License-File: LICENSE
Classifier: License :: OSI Approved :: MIT License
Classifier: Operating System :: OS Independent
Classifier: Programming Language :: Python :: 3
Requires-Python: >=3.11
Requires-Dist: aiohttp
